<?xml version="1.0" encoding="utf-8"?><AttributeDefinition xmlns:xsi="http://www.w3.org/2001/XMLSchema-instance" xmlns:xsd="http://www.w3.org/2001/XMLSchema" xsi:noNamespaceSchemaLocation="DaVinciEx_GenericAttributes_1_0.xsd" dvSchemaVersion="1.0"><AttributeDefinitionTable Version="1.0" ID="{932D3FD0-2F6C-49BF-80CB-D1C3756D3868}"><Attribute Name="IMPORT_MODE_PRESET_COMPONENT" ObjectType="ComponentType"><ENUM Default="Keep"><EnumValue Value="Keep" /><EnumValue Value="Overwrite" /></ENUM></Attribute><Attribute Name="IMPORT_MODE_PRESET_PORT" ObjectType="PortPrototype"><ENUM Default="Keep"><EnumValue Value="Keep" /><EnumValue Value="Overwrite" /></ENUM></Attribute></AttributeDefinitionTable><ObjectAttributeReference ObjectType="Port Prototype"><ARObjectReference Type="R-PORT-PROTOTYPE" Reference="/ComponentTypes/SnsrOffsCorrn/HwAg" /><AttributeDefinitionTableRef Version="1.0" ID="{932D3FD0-2F6C-49BF-80CB-D1C3756D3868}" /><AttributeValue Name="IMPORT_MODE_PRESET_PORT" Value="Overwrite" /></ObjectAttributeReference><ObjectAttributeReference ObjectType="Port Prototype"><ARObjectReference Type="P-PORT-PROTOTYPE" Reference="/ComponentTypes/SnsrOffsCorrn/HwAgCorrd" /><AttributeDefinitionTableRef Version="1.0" ID="{932D3FD0-2F6C-49BF-80CB-D1C3756D3868}" /><AttributeValue Name="IMPORT_MODE_PRESET_PORT" Value="Overwrite" /></ObjectAttributeReference><ObjectAttributeReference ObjectType="Port Prototype"><ARObjectReference Type="R-PORT-PROTOTYPE" Reference="/ComponentTypes/SnsrOffsCorrn/HwAgOffs" /><AttributeDefinitionTableRef Version="1.0" ID="{932D3FD0-2F6C-49BF-80CB-D1C3756D3868}" /><AttributeValue Name="IMPORT_MODE_PRESET_PORT" Value="Overwrite" /></ObjectAttributeReference><ObjectAttributeReference ObjectType="Port Prototype"><ARObjectReference Type="R-PORT-PROTOTYPE" Reference="/ComponentTypes/SnsrOffsCorrn/HwTq" /><AttributeDefinitionTableRef Version="1.0" ID="{932D3FD0-2F6C-49BF-80CB-D1C3756D3868}" /><AttributeValue Name="IMPORT_MODE_PRESET_PORT" Value="Overwrite" /></ObjectAttributeReference><ObjectAttributeReference ObjectType="Port Prototype"><ARObjectReference Type="P-PORT-PROTOTYPE" Reference="/ComponentTypes/SnsrOffsCorrn/HwTqCorrd" /><AttributeDefinitionTableRef Version="1.0" ID="{932D3FD0-2F6C-49BF-80CB-D1C3756D3868}" /><AttributeValue Name="IMPORT_MODE_PRESET_PORT" Value="Overwrite" /></ObjectAttributeReference><ObjectAttributeReference ObjectType="Port Prototype"><ARObjectReference Type="R-PORT-PROTOTYPE" Reference="/ComponentTypes/SnsrOffsCorrn/HwTqOffs" /><AttributeDefinitionTableRef Version="1.0" ID="{932D3FD0-2F6C-49BF-80CB-D1C3756D3868}" /><AttributeValue Name="IMPORT_MODE_PRESET_PORT" Value="Overwrite" /></ObjectAttributeReference><ObjectAttributeReference ObjectType="Port Prototype"><ARObjectReference Type="R-PORT-PROTOTYPE" Reference="/ComponentTypes/SnsrOffsCorrn/SnsrOffsCorrnHwAgLrndOffsLim" /><AttributeDefinitionTableRef Version="1.0" ID="{932D3FD0-2F6C-49BF-80CB-D1C3756D3868}" /><AttributeValue Name="IMPORT_MODE_PRESET_PORT" Value="Overwrite" /></ObjectAttributeReference><ObjectAttributeReference ObjectType="Port Prototype"><ARObjectReference Type="R-PORT-PROTOTYPE" Reference="/ComponentTypes/SnsrOffsCorrn/SnsrOffsCorrnHwTqLrndOffsLim" /><AttributeDefinitionTableRef Version="1.0" ID="{932D3FD0-2F6C-49BF-80CB-D1C3756D3868}" /><AttributeValue Name="IMPORT_MODE_PRESET_PORT" Value="Overwrite" /></ObjectAttributeReference><ObjectAttributeReference ObjectType="Port Prototype"><ARObjectReference Type="R-PORT-PROTOTYPE" Reference="/ComponentTypes/SnsrOffsCorrn/SnsrOffsCorrnOffsEna" /><AttributeDefinitionTableRef Version="1.0" ID="{932D3FD0-2F6C-49BF-80CB-D1C3756D3868}" /><AttributeValue Name="IMPORT_MODE_PRESET_PORT" Value="Overwrite" /></ObjectAttributeReference><ObjectAttributeReference ObjectType="Port Prototype"><ARObjectReference Type="R-PORT-PROTOTYPE" Reference="/ComponentTypes/SnsrOffsCorrn/SnsrOffsCorrnVehYawRateLrndOffsLim" /><AttributeDefinitionTableRef Version="1.0" ID="{932D3FD0-2F6C-49BF-80CB-D1C3756D3868}" /><AttributeValue Name="IMPORT_MODE_PRESET_PORT" Value="Overwrite" /></ObjectAttributeReference><ObjectAttributeReference ObjectType="Port Prototype"><ARObjectReference Type="R-PORT-PROTOTYPE" Reference="/ComponentTypes/SnsrOffsCorrn/VehYawRate" /><AttributeDefinitionTableRef Version="1.0" ID="{932D3FD0-2F6C-49BF-80CB-D1C3756D3868}" /><AttributeValue Name="IMPORT_MODE_PRESET_PORT" Value="Overwrite" /></ObjectAttributeReference><ObjectAttributeReference ObjectType="Port Prototype"><ARObjectReference Type="P-PORT-PROTOTYPE" Reference="/ComponentTypes/SnsrOffsCorrn/VehYawRateCorrd" /><AttributeDefinitionTableRef Version="1.0" ID="{932D3FD0-2F6C-49BF-80CB-D1C3756D3868}" /><AttributeValue Name="IMPORT_MODE_PRESET_PORT" Value="Overwrite" /></ObjectAttributeReference><ObjectAttributeReference ObjectType="Port Prototype"><ARObjectReference Type="R-PORT-PROTOTYPE" Reference="/ComponentTypes/SnsrOffsCorrn/VehYawRateOffs" /><AttributeDefinitionTableRef Version="1.0" ID="{932D3FD0-2F6C-49BF-80CB-D1C3756D3868}" /><AttributeValue Name="IMPORT_MODE_PRESET_PORT" Value="Overwrite" /></ObjectAttributeReference></AttributeDefinition>